IPYNBRENDERERBYDIP/__init__.py
IPYNBRENDERERBYDIP/custom_exceptions.py
IPYNBRENDERERBYDIP/logger.py
IPYNBRENDERERBYDIP/site.py
IPYNBRENDERERBYDIP/youtube.py
IPYNBRENDERERBYDIP-0.0.3.dist-info/LICENSE
IPYNBRENDERERBYDIP-0.0.3.dist-info/METADATA
IPYNBRENDERERBYDIP-0.0.3.dist-info/WHEEL
IPYNBRENDERERBYDIP-0.0.3.dist-info/top_level.txt
IPYNBRENDERERBYDIP-0.0.3.dist-info/RECORD
