Metadata-Version: 2.1
Name: IPYNBRENDERERBYDIP
Version: 0.0.3
Summary: This is a Small Python Package.
Home-page: https://github.com/dipdaiict/IPYNBRENDERERBYDIP
Author: dipdaiict
Author-email: dippatel256@gmail.com
License: MIT
Project-URL: Bug Tracker, https://github.com/dipdaiict/IPYNBRENDERERBYDIP/issues
Classifier: Programming Language :: Python :: 3.10
Classifier: Programming Language :: Python :: 3.11
Classifier: Programming Language :: Python :: 3.12
Classifier: Operating System :: OS Independent
Requires-Python: >3.7
License-File: LICENSE
Requires-Dist: requests
Requires-Dist: numpy
Requires-Dist: pandas
Requires-Dist: py-youtube
Requires-Dist: ensure
Provides-Extra: testing
Requires-Dist: pytest ; extra == 'testing'
Requires-Dist: mypy ; extra == 'testing'
Requires-Dist: flake8 ; extra == 'testing'
Requires-Dist: tox ; extra == 'testing'
Requires-Dist: black ; extra == 'testing'
